Workbook

Sheet Task Brief
A1: T25 Restaurant ordering chatbot
A2: Mini project | 30 marks | Build something with free LLM tools
A4: Task ID | B4: T25
A5: Task | B5: Restaurant ordering chatbot
A6: Theme | B6: Chatbots & AI assistants
A7: Suggested free tools | B7: Gemini Gems, NotebookLM, Google AI Studio or any free chatbot builder; test in the free chat apps
A8: What students do | B8: 1. Build a bot that takes an order from the menu, handles changes and computes the bill with GST. 2. Test with the sample conversations plus 10 of your own. 3. Check every bill total by hand. 4. Add rules for unavailable items and allergens.
A9: Deliverables | B9: Bot; bill verification sheet; rules; AI-use log
A10: Dataset in this file | B10: 38-item menu, restaurant info, sample test messages - 'Menu' sheet: 34 rows x 9 columns - 'Restaurant Info' sheet: 6 rows x 2 columns - 'Test Conversations' sheet: 7 rows x 2 columns
A11: About the data | B11: All data is synthetic and created for teaching; companies, people and figures are fictional. Treat it as if it were real business data. If a 'Gold Labels (evaluation)' sheet is present, do NOT give it to the AI tool - use it only at the end to measure your accuracy.
A12: Team size | B12: Individual (or pairs if your faculty allows)
A13: Responsible AI rules | B13: Use only free tools; never paste real personal or confidential data into public AI tools; verify every number the AI gives you; disclose AI-generated content.
A14: Submission | B14: 1) Build link / file / screen recording 2) This workbook with your outputs added as new sheets 3) Completed 'AI Use Log' sheet (minimum 15 entries) 4) 3-5 page report with recommendation and reflection
A16: Evaluation rubric (30 marks)
A17: Criterion | B17: What is assessed | C17: Marks | D17: Excellent | E17: Good | F17: Fair | G17: Poor
A18: 1. Working build | B18: Tool / bot / app / automation works end to end on the provided data; link, file or screen recording submitted | C18: 8 | D18: Runs fully (7-8) | E18: Minor gaps (5-6) | F18: Partly working (3-4) | G18: Not working (0-2)
A19: 2. Correctness and verification | B19: Outputs checked against the data or gold labels; accuracy measured; errors found and fixed | C19: 7 | D19: Systematic checks with numbers (6-7) | E19: Some checks (4-5) | F19: Few checks (2-3) | G19: None (0-1)
A20: 3. Prompting and iteration | B20: Clear, structured prompts; at least 3 documented improvement rounds with reasons | C20: 5 | D20: Strong iteration (5) | E20: Some iteration (3-4) | F20: Mostly one-shot (2) | G20: No log (0-1)
A21: 4. Business insight and recommendation | B21: Specific, data-backed recommendation for the stated manager or customer | C21: 6 | D21: Actionable and quantified (6) | E21: Sound but generic (4-5) | F21: Descriptive only (2-3) | G21: Missing (0-1)
A22: 5. Documentation and reflection | B22: Complete AI-use log, limitations, responsible-AI notes and personal reflection | C22: 4 | D22: Complete and honest (4) | E22: Mostly complete (3) | F22: Thin (2) | G22: Missing (0-1)
A23: Total | C23: =SUM(C18:C22) -> 30

Sheet Menu
A1: item_id | B1: category | C1: item_name | D1: price_inr | E1: food_type | F1: spice_level | G1: prep_time_min | H1: allergen_note | I1: available_today
A2: M01 | B2: Starters | C2: Paneer Tikka | D2: 260 | E2: Veg | F2: Spicy | G2: 26 | H2: Contains dairy | I2: Yes
A3: M02 | B3: Starters | C3: Chicken 65 | D3: 290 | E3: Non-veg | F3: Mild | G3: 11 | H3: Contains dairy | I3: Yes
A4: M03 | B4: Starters | C4: Hara Bhara Kebab | D4: 220 | E4: Veg | F4: Medium | G4: 13 | H4: Contains dairy | I4: Yes
A5: M04 | B5: Starters | C5: Fish Koliwada | D5: 340 | E5: Non-veg | F5: Mild | G5: 22 | I5: Yes
A6: M05 | B6: Starters | C6: Masala Papad | D6: 90 | E6: Veg | F6: Spicy | G6: 21 | H6: Contains gluten | I6: No
A7: M06 | B7: Starters | C7: Crispy Corn | D7: 210 | E7: Veg | F7: Medium | G7: 13 | H7: Contains gluten | I7: No
A8: M07 | B8: Main Course | C8: Dal Makhani | D8: 240 | E8: Veg | F8: Spicy | G8: 18 | I8: No
A9: M08 | B9: Main Course | C9: Paneer Butter Masala | D9: 280 | E9: Veg | F9: Medium | G9: 23 | H9: Contains gluten | I9: Yes
A10: M09 | B10: Main Course | C10: Butter Chicken | D10: 340 | E10: Non-veg | F10: Mild | G10: 9 | I10: No
A11: M10 | B11: Main Course | C11: Mutton Rogan Josh | D11: 420 | E11: Non-veg | F11: Mild | G11: 27 | H11: Contains gluten | I11: Yes
A12: M11 | B12: Main Course | C12: Veg Kolhapuri | D12: 250 | E12: Veg | F12: Mild | G12: 21 | H12: Contains dairy | I12: Yes
A13: M12 | B13: Main Course | C13: Chana Masala | D13: 210 | E13: Veg | F13: Medium | G13: 10 | H13: Contains gluten | I13: Yes
A14: M13 | B14: Main Course | C14: Prawn Curry | D14: 390 | E14: Non-veg | F14: Spicy | G14: 9 | I14: No
A15: M14 | B15: Breads & Rice | C15: Butter Naan | D15: 60 | E15: Veg | F15: Medium | G15: 12 | I15: Yes
A16: M15 | B16: Breads & Rice | C16: Tandoori Roti | D16: 30 | E16: Veg | F16: Spicy | G16: 15 | I16: No
A17: M16 | B17: Breads & Rice | C17: Garlic Naan | D17: 70 | E17: Veg | F17: Spicy | G17: 15 | H17: Contains dairy | I17: Yes
A18: M17 | B18: Breads & Rice | C18: Jeera Rice | D18: 150 | E18: Veg | F18: Spicy | G18: 17 | I18: No
A19: M18 | B19: Breads & Rice | C19: Veg Biryani | D19: 260 | E19: Veg | F19: Mild | G19: 11 | H19: Contains gluten | I19: No
A20: M19 | B20: Breads & Rice | C20: Chicken Biryani | D20: 320 | E20: Non-veg | F20: Mild | G20: 22 | H20: Contains nuts | I20: Yes
A21: M20 | B21: Breads & Rice | C21: Laccha Paratha | D21: 60 | E21: Veg | F21: Spicy | G21: 12 | H21: Contains dairy | I21: No
A22: M21 | B22: Maharashtrian Specials | C22: Misal Pav | D22: 140 | E22: Veg | F22: Medium | G22: 22 | I22: No
A23: M22 | B23: Maharashtrian Specials | C23: Sabudana Vada | D23: 120 | E23: Veg (Jain on request) | F23: Medium | G23: 29 | H23: Contains dairy | I23: Yes
A24: M23 | B24: Maharashtrian Specials | C24: Kolhapuri Chicken Thali | D24: 380 | E24: Non-veg | F24: Mild | G24: 29 | H24: Contains dairy | I24: Yes
A25: M24 | B25: Maharashtrian Specials | C25: Puran Poli | D25: 90 | E25: Veg | F25: Spicy | G25: 21 | I25: Yes
A26: M25 | B26: Maharashtrian Specials | C26: Pithla Bhakri | D26: 180 | E26: Veg | F26: Medium | G26: 22 | I26: No
A27: M26 | B27: Desserts | C27: Gulab Jamun | D27: 90 | E27: Veg | F27: - | G27: 19 | I27: Yes
A28: M27 | B28: Desserts | C28: Rasmalai | D28: 120 | E28: Veg | F28: - | G28: 8 | I28: Yes
A29: M28 | B29: Desserts | C29: Kulfi | D29: 100 | E29: Veg | F29: - | G29: 11 | I29: Yes
A30: M29 | B30: Desserts | C30: Chocolate Brownie | D30: 150 | E30: Contains egg | F30: - | G30: 8 | I30: Yes
A31: M30 | B31: Beverages | C31: Masala Chai | D31: 40 | E31: Veg | F31: - | G31: 23 | I31: No
A32: M31 | B32: Beverages | C32: Sweet Lassi | D32: 90 | E32: Veg | F32: - | G32: 21 | H32: Contains dairy | I32: No
A33: M32 | B33: Beverages | C33: Fresh Lime Soda | D33: 80 | E33: Veg | F33: - | G33: 20 | I33: Yes
A34: M33 | B34: Beverages | C34: Cold Coffee | D34: 130 | E34: Veg | F34: - | G34: 24 | H34: Contains nuts | I34: No
A35: M34 | B35: Beverages | C35: Kokum Sherbet | D35: 70 | E35: Veg | F35: - | G35: 18 | H35: Contains gluten | I35: Yes

Sheet Restaurant Info
A1: item | B1: details
A2: Restaurant | B2: Tambda Rassa Kitchen (fictional), Gangapur Road, Nashik
A3: Hours | B3: 12:00-15:30 and 19:00-23:30, all days
A4: Delivery radius | B4: 6 km; free above Rs 499, else Rs 40
A5: Taxes | B5: 5% GST on food bill
A6: Payment | B6: UPI, cards, cash on delivery
A7: Offer | B7: 10% off on orders above Rs 999 on weekdays

Sheet Test Conversations
A1: speaker | B1: sample_message_to_test
A2: Customer | B2: Hi, what veg starters do you have that are not spicy?
A3: Customer | B3: I want 2 paneer tikka, 1 dal makhani and 4 butter naan
A4: Customer | B4: Is there anything Jain?
A5: Customer | B5: Can I change the address after ordering?
A6: Customer | B6: What will be the total with GST?
A7: Customer | B7: Do you deliver to Satpur MIDC?
A8: Customer | B8: Add one mutton rogan josh... actually remove it, make it veg kolhapuri

Sheet Data Dictionary
A1: sheet | B1: column | C1: data_type | D1: example_value | E1: non_empty_values | F1: distinct_values
A2: Menu | B2: item_id | C2: Text | D2: M01 | E2: 34 | F2: 34
A3: Menu | B3: category | C3: Text | D3: Starters | E3: 34 | F3: 6
A4: Menu | B4: item_name | C4: Text | D4: Paneer Tikka | E4: 34 | F4: 34
A5: Menu | B5: price_inr | C5: Whole number | D5: 260 | E5: 34 | F5: 24
A6: Menu | B6: food_type | C6: Text | D6: Veg | E6: 34 | F6: 4
A7: Menu | B7: spice_level | C7: Text | D7: Spicy | E7: 34 | F7: 4
A8: Menu | B8: prep_time_min | C8: Whole number | D8: 26 | E8: 34 | F8: 18
A9: Menu | B9: allergen_note | C9: Text | D9: Contains dairy | E9: 18 | F9: 4
A10: Menu | B10: available_today | C10: Text | D10: Yes | E10: 34 | F10: 2
A11: Restaurant Info | B11: item | C11: Text | D11: Restaurant | E11: 6 | F11: 6
A12: Restaurant Info | B12: details | C12: Text | D12: Tambda Rassa Kitchen (fictional), Gangapur Road, Nashik | E12: 6 | F12: 6
A13: Test Conversations | B13: speaker | C13: Text | D13: Customer | E13: 7 | F13: 1
A14: Test Conversations | B14: sample_message_to_test | C14: Text | D14: Hi, what veg starters do you have that are not spicy? | E14: 7 | F14: 7

Sheet Bill Lines
A1: Bill Lines - items in each test's FINAL cart (typed by hand from the test scenario, not copied from the bot)
A2: Blue = hand-entered inputs (test id, item id, qty). Black = formulas pulling name / price / availability from the Menu sheet.
A4: test_id | B4: item_id | C4: item_name (lookup) | D4: qty | E4: unit price Rs (lookup) | F4: line total Rs | G4: available today? (lookup)
A5: S2 | B5: M01 | C5: =INDEX(Menu!$C$2:$C$35,MATCH(B5,Menu!$A$2:$A$35,0)) -> Paneer Tikka | D5: 2 | E5: =INDEX(Menu!$D$2:$D$35,MATCH(B5,Menu!$A$2:$A$35,0)) -> 260 | F5: =D5*E5 -> 520 | G5: =INDEX(Menu!$I$2:$I$35,MATCH(B5,Menu!$A$2:$A$35,0)) -> Yes
A6: S2 | B6: M14 | C6: =INDEX(Menu!$C$2:$C$35,MATCH(B6,Menu!$A$2:$A$35,0)) -> Butter Naan | D6: 4 | E6: =INDEX(Menu!$D$2:$D$35,MATCH(B6,Menu!$A$2:$A$35,0)) -> 60 | F6: =D6*E6 -> 240 | G6: =INDEX(Menu!$I$2:$I$35,MATCH(B6,Menu!$A$2:$A$35,0)) -> Yes
A7: S7 | B7: M11 | C7: =INDEX(Menu!$C$2:$C$35,MATCH(B7,Menu!$A$2:$A$35,0)) -> Veg Kolhapuri | D7: 1 | E7: =INDEX(Menu!$D$2:$D$35,MATCH(B7,Menu!$A$2:$A$35,0)) -> 250 | F7: =D7*E7 -> 250 | G7: =INDEX(Menu!$I$2:$I$35,MATCH(B7,Menu!$A$2:$A$35,0)) -> Yes
A8: T08 | B8: M12 | C8: =INDEX(Menu!$C$2:$C$35,MATCH(B8,Menu!$A$2:$A$35,0)) -> Chana Masala | D8: 1 | E8: =INDEX(Menu!$D$2:$D$35,MATCH(B8,Menu!$A$2:$A$35,0)) -> 210 | F8: =D8*E8 -> 210 | G8: =INDEX(Menu!$I$2:$I$35,MATCH(B8,Menu!$A$2:$A$35,0)) -> Yes
A9: T08 | B9: M08 | C9: =INDEX(Menu!$C$2:$C$35,MATCH(B9,Menu!$A$2:$A$35,0)) -> Paneer Butter Masala | D9: 1 | E9: =INDEX(Menu!$D$2:$D$35,MATCH(B9,Menu!$A$2:$A$35,0)) -> 280 | F9: =D9*E9 -> 280 | G9: =INDEX(Menu!$I$2:$I$35,MATCH(B9,Menu!$A$2:$A$35,0)) -> Yes
A10: T09 | B10: M03 | C10: =INDEX(Menu!$C$2:$C$35,MATCH(B10,Menu!$A$2:$A$35,0)) -> Hara Bhara Kebab | D10: 1 | E10: =INDEX(Menu!$D$2:$D$35,MATCH(B10,Menu!$A$2:$A$35,0)) -> 220 | F10: =D10*E10 -> 220 | G10: =INDEX(Menu!$I$2:$I$35,MATCH(B10,Menu!$A$2:$A$35,0)) -> Yes
A11: T09 | B11: M08 | C11: =INDEX(Menu!$C$2:$C$35,MATCH(B11,Menu!$A$2:$A$35,0)) -> Paneer Butter Masala | D11: 1 | E11: =INDEX(Menu!$D$2:$D$35,MATCH(B11,Menu!$A$2:$A$35,0)) -> 280 | F11: =D11*E11 -> 280 | G11: =INDEX(Menu!$I$2:$I$35,MATCH(B11,Menu!$A$2:$A$35,0)) -> Yes
A12: T10 | B12: M10 | C12: =INDEX(Menu!$C$2:$C$35,MATCH(B12,Menu!$A$2:$A$35,0)) -> Mutton Rogan Josh | D12: 2 | E12: =INDEX(Menu!$D$2:$D$35,MATCH(B12,Menu!$A$2:$A$35,0)) -> 420 | F12: =D12*E12 -> 840 | G12: =INDEX(Menu!$I$2:$I$35,MATCH(B12,Menu!$A$2:$A$35,0)) -> Yes
A13: T10 | B13: M19 | C13: =INDEX(Menu!$C$2:$C$35,MATCH(B13,Menu!$A$2:$A$35,0)) -> Chicken Biryani | D13: 1 | E13: =INDEX(Menu!$D$2:$D$35,MATCH(B13,Menu!$A$2:$A$35,0)) -> 320 | F13: =D13*E13 -> 320 | G13: =INDEX(Menu!$I$2:$I$35,MATCH(B13,Menu!$A$2:$A$35,0)) -> Yes
A14: T11 | B14: M10 | C14: =INDEX(Menu!$C$2:$C$35,MATCH(B14,Menu!$A$2:$A$35,0)) -> Mutton Rogan Josh | D14: 2 | E14: =INDEX(Menu!$D$2:$D$35,MATCH(B14,Menu!$A$2:$A$35,0)) -> 420 | F14: =D14*E14 -> 840 | G14: =INDEX(Menu!$I$2:$I$35,MATCH(B14,Menu!$A$2:$A$35,0)) -> Yes
A15: T11 | B15: M19 | C15: =INDEX(Menu!$C$2:$C$35,MATCH(B15,Menu!$A$2:$A$35,0)) -> Chicken Biryani | D15: 1 | E15: =INDEX(Menu!$D$2:$D$35,MATCH(B15,Menu!$A$2:$A$35,0)) -> 320 | F15: =D15*E15 -> 320 | G15: =INDEX(Menu!$I$2:$I$35,MATCH(B15,Menu!$A$2:$A$35,0)) -> Yes
A16: T12 | B16: M10 | C16: =INDEX(Menu!$C$2:$C$35,MATCH(B16,Menu!$A$2:$A$35,0)) -> Mutton Rogan Josh | D16: 2 | E16: =INDEX(Menu!$D$2:$D$35,MATCH(B16,Menu!$A$2:$A$35,0)) -> 420 | F16: =D16*E16 -> 840 | G16: =INDEX(Menu!$I$2:$I$35,MATCH(B16,Menu!$A$2:$A$35,0)) -> Yes
... A27: T19 | B27: M28 | C27: =INDEX(Menu!$C$2:$C$35,MATCH(B27,Menu!$A$2:$A$35,0)) -> Kulfi | D27: 1 | E27: =INDEX(Menu!$D$2:$D$35,MATCH(B27,Menu!$A$2:$A$35,0)) -> 100 | F27: =D27*E27 -> 100 | G27: =INDEX(Menu!$I$2:$I$35,MATCH(B27,Menu!$A$2:$A$35,0)) -> Yes

Sheet Bill Verification
A1: Bill Verification - every bill recalculated independently in Excel and compared with the bot's total
A2: Hand column = Excel formulas built only from the Menu sheet + the rules in the blue cells. Bot columns = numbers the chatbot printed (pasted as values from results.json).
A4: Billing parameters (from 'Restaurant Info' sheet)
A5: GST rate on food | D5: 0.05 | F5: Assumptions: (1) offer is taken off the food subtotal BEFORE GST; (2) free-delivery test uses the food subtotal BEFORE discount; (3) GST is not charged on the delivery fee ('5% GST on food bill'); (4) amounts rounded to 2 decimals (half-up).
A6: Weekday offer rate | D6: 0.1
A7: Offer applies if food subtotal is MORE than (Rs) | D7: 999
A8: Delivery fee (Rs) | D8: 40
A9: Delivery free if food subtotal is MORE than (Rs) | D9: 499
A11: test_id | B11: scenario | C11: order date | D11: weekday? (Mon-Fri) | E11: food subtotal | F11: discount | G11: after discount | H11: GST | I11: delivery | J11: HAND TOTAL (Excel) | K11: bot subtotal | L11: bot discount | M11: bot GST | N11: bot delivery | O11: BOT TOTAL | P11: difference | Q11: result
A12: S2 | B12: Order 2 paneer tikka + 1 dal makhani (UNAVAILABLE) + 4 butter naan, then ask total | C12: 46300 | D12: =IF(WEEKDAY(C12,2)<=5,"Yes","No") -> Yes | E12: =SUMIF('Bill Lines'!$A$5:$A$27,A12,'Bill Lines'!$F$5:$F$27) -> 760 | F12: =IF(AND(D12="Yes",E12>$D$7),ROUND(E12*$D$6,2),0) -> 0 | G12: =E12-F12 -> 760 | H12: =ROUND(G12*$D$5,2) -> 38 | I12: =IF(E12>$D$9,0,$D$8) -> 0 | J12: =G12+H12+I12 -> 798 | K12: 760 | L12: 0 | M12: 38 | N12: 0 | O12: 798 | P12: =ROUND(J12-O12,2) -> 0 | Q12: =IF(P12=0,"MATCH","MISMATCH") -> MATCH
A13: S7 | B13: Add mutton rogan josh, remove it, make it veg kolhapuri | C13: 46300 | D13: =IF(WEEKDAY(C13,2)<=5,"Yes","No") -> Yes | E13: =SUMIF('Bill Lines'!$A$5:$A$27,A13,'Bill Lines'!$F$5:$F$27) -> 250 | F13: =IF(AND(D13="Yes",E13>$D$7),ROUND(E13*$D$6,2),0) -> 0 | G13: =E13-F13 -> 250 | H13: =ROUND(G13*$D$5,2) -> 12.5 | I13: =IF(E13>$D$9,0,$D$8) -> 40 | J13: =G13+H13+I13 -> 302.5 | K13: 250 | L13: 0 | M13: 12.5 | N13: 40 | O13: 302.5 | P13: =ROUND(J13-O13,2) -> 0 | Q13: =IF(P13=0,"MATCH","MISMATCH") -> MATCH
A14: T08 | B14: Just below free-delivery threshold: Chana Masala + Paneer Butter Masala = 490 | C14: 46300 | D14: =IF(WEEKDAY(C14,2)<=5,"Yes","No") -> Yes | E14: =SUMIF('Bill Lines'!$A$5:$A$27,A14,'Bill Lines'!$F$5:$F$27) -> 490 | F14: =IF(AND(D14="Yes",E14>$D$7),ROUND(E14*$D$6,2),0) -> 0 | G14: =E14-F14 -> 490 | H14: =ROUND(G14*$D$5,2) -> 24.5 | I14: =IF(E14>$D$9,0,$D$8) -> 40 | J14: =G14+H14+I14 -> 554.5 | K14: 490 | L14: 0 | M14: 24.5 | N14: 40 | O14: 554.5 | P14: =ROUND(J14-O14,2) -> 0 | Q14: =IF(P14=0,"MATCH","MISMATCH") -> MATCH
A15: T09 | B15: Just above threshold: Hara Bhara Kebab + Paneer Butter Masala = 500 (delivery free) | C15: 46300 | D15: =IF(WEEKDAY(C15,2)<=5,"Yes","No") -> Yes | E15: =SUMIF('Bill Lines'!$A$5:$A$27,A15,'Bill Lines'!$F$5:$F$27) -> 500 | F15: =IF(AND(D15="Yes",E15>$D$7),ROUND(E15*$D$6,2),0) -> 0 | G15: =E15-F15 -> 500 | H15: =ROUND(G15*$D$5,2) -> 25 | I15: =IF(E15>$D$9,0,$D$8) -> 0 | J15: =G15+H15+I15 -> 525 | K15: 500 | L15: 0 | M15: 25 | N15: 0 | O15: 525 | P15: =ROUND(J15-O15,2) -> 0 | Q15: =IF(P15=0,"MATCH","MISMATCH") -> MATCH
A16: T10 | B16: Weekday discount applies: 2 Mutton Rogan Josh + 1 Chicken Biryani = 1160 (Monday) | C16: 46300 | D16: =IF(WEEKDAY(C16,2)<=5,"Yes","No") -> Yes | E16: =SUMIF('Bill Lines'!$A$5:$A$27,A16,'Bill Lines'!$F$5:$F$27) -> 1160 | F16: =IF(AND(D16="Yes",E16>$D$7),ROUND(E16*$D$6,2),0) -> 116 | G16: =E16-F16 -> 1044 | H16: =ROUND(G16*$D$5,2) -> 52.2 | I16: =IF(E16>$D$9,0,$D$8) -> 0 | J16: =G16+H16+I16 -> 1096.2 | K16: 1160 | L16: 116 | M16: 52.2 | N16: 0 | O16: 1096.2 | P16: =ROUND(J16-O16,2) -> 0 | Q16: =IF(P16=0,"MATCH","MISMATCH") -> MATCH
A17: T11 | B17: Same order on Sunday: NO discount | C17: 46299 | D17: =IF(WEEKDAY(C17,2)<=5,"Yes","No") -> No | E17: =SUMIF('Bill Lines'!$A$5:$A$27,A17,'Bill Lines'!$F$5:$F$27) -> 1160 | F17: =IF(AND(D17="Yes",E17>$D$7),ROUND(E17*$D$6,2),0) -> 0 | G17: =E17-F17 -> 1160 | H17: =ROUND(G17*$D$5,2) -> 58 | I17: =IF(E17>$D$9,0,$D$8) -> 0 | J17: =G17+H17+I17 -> 1218 | K17: 1160 | L17: 0 | M17: 58 | N17: 0 | O17: 1218 | P17: =ROUND(J17-O17,2) -> 0 | Q17: =IF(P17=0,"MATCH","MISMATCH") -> MATCH
A18: T12 | B18: Boundary 990 on weekday: no discount; nudge to unlock offer | C18: 46300 | D18: =IF(WEEKDAY(C18,2)<=5,"Yes","No") -> Yes | E18: =SUMIF('Bill Lines'!$A$5:$A$27,A18,'Bill Lines'!$F$5:$F$27) -> 990 | F18: =IF(AND(D18="Yes",E18>$D$7),ROUND(E18*$D$6,2),0) -> 0 | G18: =E18-F18 -> 990 | H18: =ROUND(G18*$D$5,2) -> 49.5 | I18: =IF(E18>$D$9,0,$D$8) -> 0 | J18: =G18+H18+I18 -> 1039.5 | K18: 990 | L18: 0 | M18: 49.5 | N18: 0 | O18: 1039.5 | P18: =ROUND(J18-O18,2) -> 0 | Q18: =IF(P18=0,"MATCH","MISMATCH") -> MATCH
A19: T13 | B19: Boundary 1000 on weekday: discount applies | C19: 46300 | D19: =IF(WEEKDAY(C19,2)<=5,"Yes","No") -> Yes | E19: =SUMIF('Bill Lines'!$A$5:$A$27,A19,'Bill Lines'!$F$5:$F$27) -> 1000 | F19: =IF(AND(D19="Yes",E19>$D$7),ROUND(E19*$D$6,2),0) -> 100 | G19: =E19-F19 -> 900 | H19: =ROUND(G19*$D$5,2) -> 45 | I19: =IF(E19>$D$9,0,$D$8) -> 0 | J19: =G19+H19+I19 -> 945 | K19: 1000 | L19: 100 | M19: 45 | N19: 0 | O19: 945 | P19: =ROUND(J19-O19,2) -> 0 | Q19: =IF(P19=0,"MATCH","MISMATCH") -> MATCH
A20: T14 | B20: Two UNAVAILABLE items, then a valid alternative | C20: 46300 | D20: =IF(WEEKDAY(C20,2)<=5,"Yes","No") -> Yes | E20: =SUMIF('Bill Lines'!$A$5:$A$27,A20,'Bill Lines'!$F$5:$F$27) -> 420 | F20: =IF(AND(D20="Yes",E20>$D$7),ROUND(E20*$D$6,2),0) -> 0 | G20: =E20-F20 -> 420 | H20: =ROUND(G20*$D$5,2) -> 21 | I20: =IF(E20>$D$9,0,$D$8) -> 40 | J20: =G20+H20+I20 -> 481 | K20: 420 | L20: 0 | M20: 21 | N20: 40 | O20: 481 | P20: =ROUND(J20-O20,2) -> 0 | Q20: =IF(P20=0,"MATCH","MISMATCH") -> MATCH
A21: T15 | B21: Nut allergy: Chicken Biryani blocked; lime soda has no allergen data -> caution | C21: 46300 | D21: =IF(WEEKDAY(C21,2)<=5,"Yes","No") -> Yes | E21: =SUMIF('Bill Lines'!$A$5:$A$27,A21,'Bill Lines'!$F$5:$F$27) -> 80 | F21: =IF(AND(D21="Yes",E21>$D$7),ROUND(E21*$D$6,2),0) -> 0 | G21: =E21-F21 -> 80 | H21: =ROUND(G21*$D$5,2) -> 4 | I21: =IF(E21>$D$9,0,$D$8) -> 40 | J21: =G21+H21+I21 -> 124 | K21: 80 | L21: 0 | M21: 4 | N21: 40 | O21: 124 | P21: =ROUND(J21-O21,2) -> 0 | Q21: =IF(P21=0,"MATCH","MISMATCH") -> MATCH
A22: T16 | B22: Quantity change: 2 gulab jamun + 1 kulfi, then make it 3 gulab jamun | C22: 46300 | D22: =IF(WEEKDAY(C22,2)<=5,"Yes","No") -> Yes | E22: =SUMIF('Bill Lines'!$A$5:$A$27,A22,'Bill Lines'!$F$5:$F$27) -> 370 | F22: =IF(AND(D22="Yes",E22>$D$7),ROUND(E22*$D$6,2),0) -> 0 | G22: =E22-F22 -> 370 | H22: =ROUND(G22*$D$5,2) -> 18.5 | I22: =IF(E22>$D$9,0,$D$8) -> 40 | J22: =G22+H22+I22 -> 428.5 | K22: 370 | L22: 0 | M22: 18.5 | N22: 40 | O22: 428.5 | P22: =ROUND(J22-O22,2) -> 0 | Q22: =IF(P22=0,"MATCH","MISMATCH") -> MATCH
A23: T17 | B23: Jain order: 2 sabudana vada | C23: 46300 | D23: =IF(WEEKDAY(C23,2)<=5,"Yes","No") -> Yes | E23: =SUMIF('Bill Lines'!$A$5:$A$27,A23,'Bill Lines'!$F$5:$F$27) -> 240 | F23: =IF(AND(D23="Yes",E23>$D$7),ROUND(E23*$D$6,2),0) -> 0 | G23: =E23-F23 -> 240 | H23: =ROUND(G23*$D$5,2) -> 12 | I23: =IF(E23>$D$9,0,$D$8) -> 40 | J23: =G23+H23+I23 -> 292 | K23: 240 | L23: 0 | M23: 12 | N23: 40 | O23: 292 | P23: =ROUND(J23-O23,2) -> 0 | Q23: =IF(P23=0,"MATCH","MISMATCH") -> MATCH
... A25: T19 | B25: Closed hours (4 pm): cart ok, order cannot be placed; then place at 7:30 pm with address | C25: 46300 | D25: =IF(WEEKDAY(C25,2)<=5,"Yes","No") -> Yes | E25: =SUMIF('Bill Lines'!$A$5:$A$27,A25,'Bill Lines'!$F$5:$F$27) -> 100 | F25: =IF(AND(D25="Yes",E25>$D$7),ROUND(E25*$D$6,2),0) -> 0 | G25: =E25-F25 -> 100 | H25: =ROUND(G25*$D$5,2) -> 5 | I25: =IF(E25>$D$9,0,$D$8) -> 40 | J25: =G25+H25+I25 -> 145 | K25: 100 | L25: 0 | M25: 5 | N25: 40 | O25: 145 | P25: =ROUND(J25-O25,2) -> 0 | Q25: =IF(P25=0,"MATCH","MISMATCH") -> MATCH
A27: Summary
A28: Bills checked | E28: =COUNTA(A12:A25) -> 14
A29: Bills matching to the paisa | E29: =COUNTIF(Q12:Q25,"MATCH") -> 14
A30: Accuracy | E30: =E29/E28 -> 1
A31: Largest absolute difference (Rs) | E31: =SUMPRODUCT(MAX(ABS(P12:P25))) -> #VALUE!
A33: Also hand-checked on paper (examples): S2 = 2x260 + 4x60 = 760; GST 38.00; delivery free; 798.00. T10 (Mon) = 1160 - 116 = 1044; GST 52.20; 1,096.20. T08 = 490 + 24.50 + 40 = 554.50.

Sheet Rules
A1: Rules - what the bot must always do (implemented in bot.py; copied into the Gemini Gem / Google AI Studio system instructions)
A2: Every rule has at least one test that proves it (see 'Test Log').
A4: rule id | B4: area | C4: rule | D4: why (source in the data) | E4: tested by
A5: R01 | B5: Menu | C5: Only offer / add items whose available_today = 'Yes'. 14 of 34 items are 'No' today. | D5: Menu!I | E5: S2, T14
A6: R02 | B6: Unavailable | C6: If a customer asks for an unavailable item: do NOT add it, say so, suggest up to 3 available items from the same category (same veg/non-veg type first), keep the rest of the order. | D6: Menu!I, Menu!B, Menu!E | E6: S2, T14
A7: R03 | B7: Ordering | C7: Quantity defaults to 1; words (one, two, a) and digits both work; max 20 of one item - above that ask them to phone the restaurant. | D7: Kitchen capacity guard (assumption) | E7: S2, T10
A8: R04 | B8: Ordering | C8: If a name matches several items ('naan', 'paneer', 'chicken') ask which one - never guess. Fix small typos ('panner'); if the item is not on the menu say so and suggest close names. | D8: Menu!C | E8: T18
A9: R05 | B9: Changes | C9: Support add, remove, reduce, 'make it 3', 'make it <other item>', 'replace X with Y'. 'it' = the last item touched. | D9: Sample message 7 | E9: S7, T16
A10: R06 | B10: Bill | C10: Food subtotal = sum(price x qty). GST = 5% of the amount AFTER discount, rounded to 2 decimals (half-up). GST is not charged on delivery. | D10: Restaurant Info: '5% GST on food bill' | E10: all bills
A11: R07 | B11: Bill | C11: Delivery Rs 40, FREE when food subtotal is MORE than Rs 499 (Rs 499 exactly pays Rs 40). Test uses subtotal before discount. | D11: Restaurant Info: delivery | E11: T08 (490), T09 (500)
A12: R08 | B12: Bill | C12: 10% off ONLY when food subtotal is MORE than Rs 999 AND the order date is Mon-Fri. Rs 999 exactly gets nothing; weekends get nothing. | D12: Restaurant Info: offer | E12: T10, T11, T12 (990), T13 (1000)
A13: R09 | B13: Bill | C13: Never state a total from memory: the code computes it; the Gemini Gem must show line-by-line working. With an empty cart, ask for the order instead of inventing a total. | D13: Verification requirement | E13: S5, all bills
A14: R10 | B14: Upsell | C14: If the customer is within Rs 100 of free delivery / the weekday offer, show one tip with the exact extra amount. Never push the tip if far away. | D14: Business insight (see Recommendation) | E14: T08, T12
A15: R11 | B15: Allergen | C15: Allergen words understood: nuts, dairy, gluten, egg, fish, shellfish (prawn). When a customer declares an allergy, remember it for the whole chat. | D15: Menu!H | E15: T15
... A26: R22 | B26: Privacy | C26: Never ask for or store real personal data in public AI tools; test with fictional addresses only. | D26: Task Brief: Responsible AI rules | E26: T19

Sheet Test Log
A1: Test Log - 7 sample conversations (S1-S7) + 12 of my own (T08-T19)
A2: Run by run_tests.py against the live bot. Expected totals were worked out by hand BEFORE running. PASS = bill matches to the paisa AND the required rule wording appeared.
A4: test id | B4: type | C4: scenario | D4: simulated date/time | E4: conversation (YOU -> BOT) | F4: expected total (hand) | G4: bot total | H4: result
A5: S1 | B5: sample | C5: Veg starters that are not spicy | D5: 10/5/26 Mon 13:00 | E5: YOU: Hi, what veg starters do you have that are not spicy? BOT: There are no mild-spice veg starters available today. Closest (Medium spice, not 'Spicy'): Hara Bhara Kebab (Rs 220, Veg, Medium; contains dairy) Avoid (Spicy): Paneer Tikka Not available today: Masala Papad, Crispy Corn | F5: n/a (no bill) | G5: n/a | H5: PASS
A6: S2 | B6: sample | C6: Order 2 paneer tikka + 1 dal makhani (UNAVAILABLE) + 4 butter naan, then ask total | D6: 10/5/26 Mon 13:00 | E6: YOU: I want 2 paneer tikka, 1 dal makhani and 4 butter naan BOT: Added 2 x Paneer Tikka (Rs 260 each). Note: Contains dairy. Sorry, Dal Makhani is not available today, so I have not added it. Similar options available: Paneer Butter Masala (Rs 280), Veg Kolhapuri (Rs 250), Chana Masala (Rs 210). Added 4 x Butter Naan (Rs 60 each). YOU: What will be the total with GST? BOT: Here is your bill: 2 x Paneer Tikka @ Rs 260 = Rs 520.00 4 x Butter Naan @ Rs 60 = Rs 240.00 Food subtotal: Rs 760.00 GST @5% on Rs 760.00: Rs 38.00 Delivery: FREE (food above Rs 499) TOTAL PAYABLE: Rs 798.00 | F6: 798 | G6: 798 | H6: PASS
A7: S3 | B7: sample | C7: Jain query | D7: 10/5/26 Mon 13:00 | E7: YOU: Is there anything Jain? BOT: Yes - Sabudana Vada (Rs 120; 'Veg (Jain on request)'; Contains dairy) can be made Jain on request. It is the only item marked Jain in our menu - please tell the kitchen your Jain requirements when ordering. I can't promise other dishes are Jain. | F7: n/a (no bill) | G7: n/a | H7: PASS
A8: S4 | B8: sample | C8: Change address after ordering (info not in data -> must not promise) | D8: 10/5/26 Mon 13:00 | E8: YOU: Can I change the address after ordering? BOT: Yes - nothing is final until you confirm. I'll ask for the delivery address at the end. After the order is placed, changing the address isn't guaranteed, so please check it carefully. | F8: n/a (no bill) | G8: n/a | H8: PASS
A9: S5 | B9: sample | C9: Total with GST when cart is empty (must ask for order, not invent a number) | D9: 10/5/26 Mon 13:00 | E9: YOU: What will be the total with GST? BOT: I can compute that as soon as I know your order - what would you like? For reference: bill = food subtotal (- 10% on weekdays above Rs 999) + 5% GST + Rs 40 delivery if food is Rs 499 or less. | F9: n/a (no bill) | G9: n/a | H9: PASS
A10: S6 | B10: sample | C10: Delivery to Satpur MIDC (distance unknown -> must not guess) | D10: 10/5/26 Mon 13:00 | E10: YOU: Do you deliver to Satpur MIDC? BOT: I can't measure the distance to Satpur MIDC myself. We deliver within a 6 km radius of Tambda Rassa Kitchen (Gangapur Road, Nashik). Delivery is free for food above Rs 499, otherwise Rs 40. Please share your full address or pin and the restaurant will confirm it is inside the radius before dispatch. | F10: n/a (no bill) | G10: n/a | H10: PASS
A11: S7 | B11: sample | C11: Add mutton rogan josh, remove it, make it veg kolhapuri | D11: 10/5/26 Mon 13:00 | E11: YOU: Add one mutton rogan josh... actually remove it, make it veg kolhapuri BOT: Added 1 x Mutton Rogan Josh (Rs 420 each). Note: Contains gluten. Removed Mutton Rogan Josh from your order. Added 1 x Veg Kolhapuri (Rs 250 each). Note: Contains dairy. YOU: total BOT: Here is your bill: 1 x Veg Kolhapuri @ Rs 250 = Rs 250.00 Food subtotal: Rs 250.00 GST @5% on Rs 250.00: Rs 12.50 Delivery: Rs 40.00 TOTAL PAYABLE: Rs 302.50 | F11: 302.5 | G11: 302.5 | H11: PASS
A12: T08 | B12: own | C12: Just below free-delivery threshold: Chana Masala + Paneer Butter Masala = 490 | D12: 10/5/26 Mon 13:00 | E12: YOU: I want 1 chana masala and 1 paneer butter masala BOT: Added 1 x Chana Masala (Rs 210 each). Note: Contains gluten. Added 1 x Paneer Butter Masala (Rs 280 each). Note: Contains gluten. YOU: bill BOT: Here is your bill: 1 x Chana Masala @ Rs 210 = Rs 210.00 1 x Paneer Butter Masala @ Rs 280 = Rs 280.00 Food subtotal: Rs 490.00 GST @5% on Rs 490.00: Rs 24.50 Delivery: Rs 40.00 TOTAL PAYABLE: Rs 554.50 Tip: add Rs 10 more food to get free delivery (saves Rs 40). | F12: 554.5 | G12: 554.5 | H12: PASS
A13: T09 | B13: own | C13: Just above threshold: Hara Bhara Kebab + Paneer Butter Masala = 500 (delivery free) | D13: 10/5/26 Mon 13:00 | E13: YOU: 1 hara bhara kebab and 1 paneer butter masala BOT: Added 1 x Hara Bhara Kebab (Rs 220 each). Note: Contains dairy. Added 1 x Paneer Butter Masala (Rs 280 each). Note: Contains gluten. YOU: bill BOT: Here is your bill: 1 x Hara Bhara Kebab @ Rs 220 = Rs 220.00 1 x Paneer Butter Masala @ Rs 280 = Rs 280.00 Food subtotal: Rs 500.00 GST @5% on Rs 500.00: Rs 25.00 Delivery: FREE (food above Rs 499) TOTAL PAYABLE: Rs 525.00 | F13: 525 | G13: 525 | H13: PASS
A14: T10 | B14: own | C14: Weekday discount applies: 2 Mutton Rogan Josh + 1 Chicken Biryani = 1160 (Monday) | D14: 10/5/26 Mon 13:00 | E14: YOU: Please add 2 mutton rogan josh and a chicken biryani BOT: Added 2 x Mutton Rogan Josh (Rs 420 each). Note: Contains gluten. Added 1 x Chicken Biryani (Rs 320 each). Note: Contains nuts. YOU: total BOT: Here is your bill: 2 x Mutton Rogan Josh @ Rs 420 = Rs 840.00 1 x Chicken Biryani @ Rs 320 = Rs 320.00 Food subtotal: Rs 1,160.00 Weekday offer (10% off, food > Rs 999): -Rs 116.00 Amount after discount: Rs 1,044.00 GST @5% on Rs 1,044.00: Rs 52.20 Delivery: FREE (food above Rs 499) TOTAL PAYABLE: Rs 1,096.20 | F14: 1096.2 | G14: 1096.2 | H14: PASS
A15: T11 | B15: own | C15: Same order on Sunday: NO discount | D15: 10/4/26 Sun 13:00 | E15: YOU: Please add 2 mutton rogan josh and a chicken biryani BOT: Added 2 x Mutton Rogan Josh (Rs 420 each). Note: Contains gluten. Added 1 x Chicken Biryani (Rs 320 each). Note: Contains nuts. YOU: total BOT: Here is your bill: 2 x Mutton Rogan Josh @ Rs 420 = Rs 840.00 1 x Chicken Biryani @ Rs 320 = Rs 320.00 Food subtotal: Rs 1,160.00 GST @5% on Rs 1,160.00: Rs 58.00 Delivery: FREE (food above Rs 499) TOTAL PAYABLE: Rs 1,218.00 | F15: 1218 | G15: 1218 | H15: PASS
A16: T12 | B16: own | C16: Boundary 990 on weekday: no discount; nudge to unlock offer | D16: 10/5/26 Mon 13:00 | E16: YOU: 2 mutton rogan josh and 1 chocolate brownie BOT: Added 2 x Mutton Rogan Josh (Rs 420 each). Note: Contains gluten. Added 1 x Chocolate Brownie (Rs 150 each). Note: contains egg. YOU: bill BOT: Here is your bill: 2 x Mutton Rogan Josh @ Rs 420 = Rs 840.00 1 x Chocolate Brownie @ Rs 150 = Rs 150.00 Food subtotal: Rs 990.00 GST @5% on Rs 990.00: Rs 49.50 Delivery: FREE (food above Rs 499) TOTAL PAYABLE: Rs 1,039.50 Tip: add Rs 10 more food today to unlock 10% off (weekday offer). | F16: 1039.5 | G16: 1039.5 | H16: PASS
A17: T13 | B17: own | C17: Boundary 1000 on weekday: discount applies | D17: 10/5/26 Mon 13:00 | E17: YOU: 2 mutton rogan josh, 1 gulab jamun and 1 garlic naan BOT: Added 2 x Mutton Rogan Josh (Rs 420 each). Note: Contains gluten. Added 1 x Gulab Jamun (Rs 90 each). Added 1 x Garlic Naan (Rs 70 each). Note: Contains dairy. YOU: bill BOT: Here is your bill: 2 x Mutton Rogan Josh @ Rs 420 = Rs 840.00 1 x Gulab Jamun @ Rs 90 = Rs 90.00 1 x Garlic Naan @ Rs 70 = Rs 70.00 Food subtotal: Rs 1,000.00 Weekday offer (10% off, food > Rs 999): -Rs 100.00 Amount after discount: Rs 900.00 GST @5% on Rs 900.00: Rs 45.00 Delivery: FREE (food above Rs 499) TOTAL PAYABLE: Rs 945.00 | F17: 945 | G17: 945 | H17: PASS
A18: T14 | B18: own | C18: Two UNAVAILABLE items, then a valid alternative | D18: 10/5/26 Mon 13:00 | E18: YOU: Add prawn curry and butter chicken BOT: Sorry, Prawn Curry is not available today, so I have not added it. Similar options available: Mutton Rogan Josh (Rs 420). Sorry, Butter Chicken is not available today, so I have not added it. Similar options available: Mutton Rogan Josh (Rs 420). YOU: ok 1 mutton rogan josh BOT: Added 1 x Mutton Rogan Josh (Rs 420 each). Note: Contains gluten. YOU: total BOT: Here is your bill: 1 x Mutton Rogan Josh @ Rs 420 = Rs 420.00 Food subtotal: Rs 420.00 GST @5% on Rs 420.00: Rs 21.00 Delivery: Rs 40.00 TOTAL PAYABLE: Rs 481.00 Tip: add Rs 80 more food to get free delivery (saves Rs 40). | F18: 481 | G18: 481 | H18: PASS
A19: T15 | B19: own | C19: Nut allergy: Chicken Biryani blocked; lime soda has no allergen data -> caution | D19: 10/5/26 Mon 13:00 | E19: YOU: I'm allergic to nuts. 1 chicken biryani and 1 fresh lime soda BOT: Noted - I'll flag any dish with: nuts. Dishes with no allergen info on file will be marked 'unconfirmed'. ALLERGY ALERT: Chicken Biryani contains nuts, and you told me you are allergic. I have NOT added it. Reply 'yes add anyway' to add it, or pick something else. Added 1 x Fresh Lime Soda (Rs 80 each). Caution: our menu has no allergen information for Fresh Lime Soda, so I cannot confirm it is free of nuts. Please confirm with the kitchen before eating. YOU: no BOT: OK, I've left it out. What else would you like? YOU: total BOT: Here is your bill: 1 x Fresh Lime Soda @ Rs 80 = Rs 80.00 Food subtotal: Rs 80.00 GST @5% on Rs 80.00: Rs 4.00 Delivery: Rs 40.00 TOTAL PAYABLE: Rs 124.00 | F19: 124 | G19: 124 | H19: PASS
A20: T16 | B20: own | C20: Quantity change: 2 gulab jamun + 1 kulfi, then make it 3 gulab jamun | D20: 10/5/26 Mon 13:00 | E20: YOU: 2 gulab jamun and 1 kulfi BOT: Added 2 x Gulab Jamun (Rs 90 each). Added 1 x Kulfi (Rs 100 each). YOU: make it 3 gulab jamun BOT: Updated: 3 x Gulab Jamun. YOU: total BOT: Here is your bill: 3 x Gulab Jamun @ Rs 90 = Rs 270.00 1 x Kulfi @ Rs 100 = Rs 100.00 Food subtotal: Rs 370.00 GST @5% on Rs 370.00: Rs 18.50 Delivery: Rs 40.00 TOTAL PAYABLE: Rs 428.50 | F20: 428.5 | G20: 428.5 | H20: PASS
A21: T17 | B21: own | C21: Jain order: 2 sabudana vada | D21: 10/5/26 Mon 13:00 | E21: YOU: 2 sabudana vada jain please BOT: Added 2 x Sabudana Vada (Rs 120 each). Note: Contains dairy. YOU: total BOT: Here is your bill: 2 x Sabudana Vada @ Rs 120 = Rs 240.00 Food subtotal: Rs 240.00 GST @5% on Rs 240.00: Rs 12.00 Delivery: Rs 40.00 TOTAL PAYABLE: Rs 292.00 | F21: 292 | G21: 292 | H21: PASS
A22: T18 | B22: own | C22: Typos + unknown item: 'panner tikka', 'pizza', ambiguous 'naan' | D22: 10/5/26 Mon 13:00 | E22: YOU: 2 panner tikka and 1 pizza and 1 naan BOT: Added 2 x Paneer Tikka (Rs 260 each). Note: Contains dairy. Sorry, I couldn't find 'pizza' on our menu. Which 'naan' do you mean? Butter Naan (Rs 60), Garlic Naan (Rs 70). YOU: total BOT: Here is your bill: 2 x Paneer Tikka @ Rs 260 = Rs 520.00 Food subtotal: Rs 520.00 GST @5% on Rs 520.00: Rs 26.00 Delivery: FREE (food above Rs 499) TOTAL PAYABLE: Rs 546.00 | F22: 546 | G22: 546 | H22: PASS
A23: T19 | B23: own | C23: Closed hours (4 pm): cart ok, order cannot be placed; then place at 7:30 pm with address | D23: 10/5/26 Mon 16:00 | E23: YOU: 1 kulfi BOT: Added 1 x Kulfi (Rs 100 each). YOU: confirm BOT: We're closed right now (open 12:00-15:30 and 19:00-23:30 daily), so I can't place the order yet. Your cart is saved. YOU: [19:30 same cart] 1 kulfi BOT: Added 1 x Kulfi (Rs 100 each). YOU: confirm BOT: Here is your bill: 1 x Kulfi @ Rs 100 = Rs 100.00 Food subtotal: Rs 100.00 GST @5% on Rs 100.00: Rs 5.00 Delivery: Rs 40.00 TOTAL PAYABLE: Rs 145.00 Please share your delivery address (we deliver within 6 km of Gangapur Road, Nashik). YOU: Flat 12, Gangapur Road, Nashik BOT: Order #001 placed for delivery to: Flat 12, Gangapur Road, Nashik. Here is your bill: 1 x Kulfi @ Rs 100 = Rs 100.00 Food subtotal: Rs 100.00 GST @5% on Rs 100.00: Rs 5.00 Delivery: Rs 40.00 TOTAL PAYABLE: Rs 145.00 Payment: UPI, card or cash on delivery. Thank you - Tambda Rassa Kitchen! | F23: n/a (no bill) | G23: n/a | H23: PASS
A25: Passed | C25: =COUNTIF(H5:H23,"PASS")&" of "&COUNTA(H5:H23) -> 19 of 19

Sheet Recommendation
A1: Business analysis, recommendation and limitations - Tambda Rassa Kitchen ordering bot
A4: A. First 3 steps to build it - and what could go wrong
A5: Step 1 - Audit the data before building | B5: Read Menu, Restaurant Info and Test Conversations; list gaps and ambiguous rules. | C5: Could go wrong: bot is built on wrong assumptions (e.g. brief says 38 items, sheet has 34; 16 allergen cells blank). | D5: Done - see section B.
A6: Step 2 - Write the rules, then the bill engine | B6: Fix GST/discount/delivery order of operations, unavailable-item and allergen rules; compute money in code (Decimal), not in the LLM. | C6: Could go wrong: LLM does arithmetic mentally and is off by a few rupees; discount applied on weekends; GST charged before discount. | D6: Mitigation: code engine + Excel cross-check (Bill Verification).
A7: Step 3 - Build the conversation layer and test hard | B7: Parse orders/changes, add allergy + unavailable handling, then run the 7 samples + 10-plus own tests and verify every bill by hand. | C7: Could go wrong: ambiguous names ('naan'), typos, 'it' references, guessed delivery areas, promises about address changes that the data does not support. | D7: Mitigation: Test Log (19 conversations), Rules R04, R18, R19.
A9: B. What the data shows (live formulas on the Menu sheet)
A10: Menu items in sheet | B10: =COUNTA(Menu!A2:A35) -> 34 | C10: Task Brief says 38 - the sheet has 34. Reported, not silently changed.
A11: Unavailable today | B11: =COUNTIF(Menu!I2:I35,"No") -> 14 | C11: =B11/B10 -> 0.41176471
A12: Main Course available / total | B12: =COUNTIFS(Menu!B2:B35,"Main Course",Menu!I2:I35,"Yes")&" of "&COUNTIF(Menu!B2:B35,"Main Course") -> 4 of 7 | C12: Dal Makhani, Butter Chicken and Prawn Curry are all unavailable.
A13: Breads & Rice available / total | B13: =COUNTIFS(Menu!B2:B35,"Breads & Rice",Menu!I2:I35,"Yes")&" of "&COUNTIF(Menu!B2:B35,"Breads & Rice") -> 3 of 7 | C13: Tandoori Roti, Jeera Rice, Veg Biryani, Laccha Paratha unavailable.
A14: Blank allergen notes | B14: =COUNTBLANK(Menu!H2:H35) -> 16 | C14: A blank is 'unknown', not 'safe'. Includes Fish Koliwada and Prawn Curry (fish/shellfish).
A15: Blank allergen AND available today | B15: =SUMPRODUCT((Menu!H2:H35="")*(Menu!I2:I35="Yes")) -> 8 | C15: These are the items the bot would have to describe as 'unconfirmed' to an allergic customer.
A16: Prep-time range (min) | B16: =MIN(Menu!G2:G35)&" - "&MAX(Menu!G2:G35) -> 8 - 29 | C16: Masala Chai 23 min vs Butter Chicken 9 min: looks unreliable, so the bot does not quote prep times.
A17: Cheapest available add-on (Rs) | B17: =_xlfn.MINIFS(Menu!D2:D35,Menu!I2:I35,"Yes") -> 60 | C17: Butter Naan - the smallest add-on available for free-delivery nudges (Masala Chai Rs 40 is unavailable today).
A19: C. Recommendation to the restaurant manager (specific, from the data and the 19 tests)
A20: 1. Fix allergen data before public launch. | B20: 16 of 34 items (47%) have no allergen note, including every fish/prawn dish. Have the kitchen complete the column in one sitting (about 16 cells). Until then the bot shows 'unconfirmed' - safe, but it makes allergic customers phone the restaurant.
A21: 2. Keep the bot's live availability filter, and update 'available_today' each morning. | B21: 14 of 34 items (41%) are unavailable today, including 3 of 7 mains and 4 of 7 breads/rice. Without the filter, roughly 2 in 5 random menu picks would be a dead end. A shared sheet the bot reads makes this a 2-minute daily task.
A22: 3. Keep the 'add Rs X more' tips. | B22: Free delivery starts at food > Rs 499: an order of Rs 490 pays Rs 554.50 (T08); Rs 500 pays Rs 525.00 (T09) - a Rs 10 bigger basket saves the customer Rs 29.50 in total. The weekday offer is a steeper cliff: Rs 990 food pays Rs 1,039.50 (T12) but Rs 1,000 food pays Rs 945.00 (T13). Both are strong, honest nudges - but the 10% cliff costs the restaurant about Rs 100 on every Rs 1,000 order, so check food margin before keeping the 999 threshold.
A23: 4. Make the weekend rule visible. | B23: The offer is Mon-Fri only (T11: same Rs 1,160 basket pays Rs 1,218.00 on Sunday vs Rs 1,096.20 on Monday - Rs 121.80 more). The bot states this up front to avoid disputes; add it to the menu card too.
A24: 5. Decide three policies the data is silent on, then add them as rules: | B24: address change after ordering, an exact delivery-area list (e.g. is Satpur MIDC inside 6 km?), and prep-time/ETA quoting. Today the bot refuses to guess on all three.
A25: 6. Pilot before full launch. | B25: Run 2 weeks with staff confirming each order; track (a) bills that staff had to correct, (b) allergy escalations, (c) % of nudges accepted. Target: 0 incorrect bills (14/14 bills correct in testing) before removing staff check.
A27: D. Assumptions, limitations and responsible-AI notes
A28: Assumptions | B28: GST on discounted food amount; free-delivery test on pre-discount food subtotal; delivery not taxed; 'weekday' = Mon-Fri by the order date; bill rounded half-up to 2 decimals.
A29: Limitations | B29: Rule-based language understanding: unusual phrasings can fall back to a help message. Cannot measure distance. No payments, no live kitchen stock (relies on available_today). The Python bot was tested here on synthetic data with a simulated clock/date; the Google AI Studio build is documented separately in AI Use Log #8-#15.
A30: Allergens | B30: The bot is a helper, never a medical guarantee. Name-based inference is a safety net, flagged as 'not in data'.
A31: Responsible AI | B31: Synthetic data only; no real personal data; every bill was recomputed independently in Excel; AI-generated parts are disclosed in the AI Use Log (#1-#15: student's ChatGPT / Google AI Studio use; #16-#30: Claude, used to build the Python bot, rules, tests and workbook sheets). 'Gold Labels' sheet: not present in this file.
A32: Personal reflection (write in your own words) | B32: << STUDENT TO WRITE 4-6 lines: what you learned, what surprised you (e.g. a blank allergen cell is not 'safe'), what you would do differently. >>

Sheet AI Use Log
A1: AI Use Log - one row per prompt (minimum 15). Entries #1-#15: student (ChatGPT / Google AI Studio). Entries #16-#30: Claude, used to build the Python bot, rules, tests and workbook sheets (disclosed).
A2: Evidence = shared chat link or screenshot file name. Keep rejected outputs too - they earn marks under 'Prompting and iteration'.
A3: # | B3: date | C3: tool | D3: model / mode | E3: settings used (if any) | F3: prompt (exact text) | G3: what the output did well / badly | H3: what I changed next and why | I3: kept or rejected | J3: evidence link / file
A4: 1 | B4: 46290 | C4: ChatGPT | D4: GPT-5.6 Luna | E4: Default | F4: Asked for help understanding the restaurant chatbot assignment and its requirements. | G4: Identified ordering, billing, GST, availability, allergen handling and testing requirements. | H4: Converted the assignment into a development checklist. | I4: Kept
A5: 2 | B5: 46290 | C5: ChatGPT | D5: GPT-5.6 Luna | E5: Default | F5: Asked how to approach the chatbot using the restaurant Excel dataset. | G5: Suggested treating the Excel menu as the source of truth instead of allowing AI to invent prices or availability. | H5: Decided to separate conversational AI from business-rule validation. | I5: Kept
A6: 3 | B6: 46291 | C6: ChatGPT | D6: GPT-5.6 Luna | E6: Default | F6: Asked why an initial chatbot was accepting unavailable menu items. | G6: Identified the issue as lack of deterministic validation and possible LLM hallucination. | H6: Added explicit availability validation before accepting an item. | I6: Kept
A7: 4 | B7: 46291 | C7: ChatGPT | D7: GPT-5.6 Luna | E7: Default | F7: Asked for Python logic to read the restaurant workbook and validate menu items. | G7: Generated logic for reading menu data, checking availability and calculating bills. | H7: Tested the logic against the actual workbook structure. | I7: Kept
A8: 5 | B8: 46292 | C8: ChatGPT | D8: GPT-5.6 Luna | E8: Default | F8: Provided Restaurant Info and Test Conversations and asked for chatbot rules to be aligned with them. | G8: Incorporated GST, delivery charges, discount conditions and sample conversations. | H8: Used supplied restaurant rules as the source of truth. | I8: Kept
A9: 6 | B9: 46293 | C9: ChatGPT | D9: GPT-5.6 Luna | E9: Default | F9: Asked for a revised version of the chatbot after identifying issues in the first implementation. | G9: Improved order changes, unavailable-item handling and deterministic billing. | H9: Used the revised logic as the basis for the final chatbot design. | I9: Kept
A10: 7 | B10: 46294 | C10: ChatGPT | D10: GPT-5.6 Luna | E10: Default | F10: Asked how to convert the terminal chatbot into a proper user-facing chatbot without using the terminal. | G10: Recommended Google AI Studio Build Mode as a suitable free application-building option. | H10: Chose Google AI Studio for the final UI implementation. | I10: Kept
A11: 8 | B11: 46294 | C11: Google AI Studio | D11: Build Mode | E11: Default | F11: Prompted AI Studio to build a restaurant ordering chatbot using the assignment requirements, restaurant information and menu rules. | G11: Generated a functional conversational chatbot interface. | H11: Reviewed the application and identified areas requiring stronger business-rule enforcement. | I11: Kept
A12: 9 | B12: 46295 | C12: Google AI Studio | D12: Build Mode | E12: Default | F12: Instructed the chatbot to use the supplied menu as the source of truth for prices and availability. | G12: Reduced the risk of inventing menu items or accepting unavailable items. | H12: Strengthened menu-validation instructions and application logic. | I12: Kept
A13: 10 | B13: 46295 | C13: Google AI Studio | D13: Build Mode | E13: Default | F13: Tested an order containing 2 Paneer Tikka, 1 Dal Makhani and 4 Butter Naan. | G13: Correctly identified that Dal Makhani was unavailable while the other requested items were available. | H13: Ensured unavailable items were not silently added to the cart. | I13: Kept
A14: 11 | B14: 46296 | C14: Google AI Studio | D14: Build Mode | E14: Default | F14: Tested: “Add one mutton rogan josh… actually remove it, make it veg kolhapuri.” | G14: Tested whether the chatbot followed the latest customer instruction. | H14: Ensured Mutton Rogan Josh was removed and Veg Kolhapuri became the final item. | I14: Kept
A15: 12 | B15: 46297 | C15: Google AI Studio | D15: Build Mode | E15: Default | F15: Tested GST and bill calculation using the restaurant’s 5% GST rule. | G15: Generated the bill based on menu prices and GST. | H15: Manually calculated the bill and compared it with the chatbot result. | I15: Kept
... A18: 15 | B18: 46299 | C18: Google AI Studio | D18: Build Mode | E18: Final version | F18: Conducted final end-to-end testing covering menu selection, availability, order modification, allergens, GST, discount and delivery rules. | G18: Final chatbot provided a user-friendly ordering experience while following the supplied business rules. | H18: Final version retained for demonstration, screen recording and submission. | I18: Kept – Final
